cPredictor/SVM_prediction.py
cPredictor/__init__.py
cPredictor/tests/SVM_prediction_test.py
cPredictor/tests/__init__.py
cPredictor/tests/cPredictor_test_model.py
cpredictor-0.5.0.dist-info/licenses/LICENSE
cpredictor-0.5.0.dist-info/METADATA
cpredictor-0.5.0.dist-info/WHEEL
cpredictor-0.5.0.dist-info/entry_points.txt
cpredictor-0.5.0.dist-info/top_level.txt
cpredictor-0.5.0.dist-info/RECORD
