Metadata-Version: 2.4
Name: cPredictor
Version: 0.5.0
Summary: Cell command line predictor
License-File: LICENSE
Requires-Dist: setuptools==68.2.2
Requires-Dist: wheel
Requires-Dist: python-build
Requires-Dist: pytest-cov
Requires-Dist: h5py
Requires-Dist: numpy<1.24,>=1.23.3
Requires-Dist: pandas>=1.4.4
Requires-Dist: scikit-learn
Requires-Dist: scanpy>=1.9.1
Requires-Dist: importlib-resources
Requires-Dist: pytest-cov
Requires-Dist: pyarrow<16,>=4.0.0
Requires-Dist: scikit-learn-intelex
Dynamic: description
Dynamic: description-content-type
Dynamic: license-file
